<?xml version="1.0" encoding="utf-8" ?><dwsync><file name="autoload.php" server="christianbrooks.net" local="3602631072" remote="318763443984161592" Dst="-1" /><file name="config.php" server="christianbrooks.net" local="3602631072" remote="318763443987626052" Dst="-1" /><file name="constants.php" server="christianbrooks.net" local="3602631072" remote="318763443983991312" Dst="-1" /><file name="database.php" server="christianbrooks.net" local="3602631073" remote="318763443984161652" Dst="-1" /><file name="doctypes.php" server="christianbrooks.net" local="3602631073" remote="318763443983991312" Dst="-1" /><file name="foreign_chars.php" server="christianbrooks.net" local="3602631073" remote="318763443983991312" Dst="-1" /><file name="hooks.php" server="christianbrooks.net" local="3602631073" remote="318763443983991312" Dst="-1" /><file name="index.html" server="christianbrooks.net" local="3602631074" remote="318763443983991312" Dst="-1" /><file name="memcached.php" server="christianbrooks.net" local="3602631074" remote="318763443983991312" Dst="-1" /><file name="migration.php" server="christianbrooks.net" local="3602631075" remote="318763443983991312" Dst="-1" /><file name="mimes.php" server="christianbrooks.net" local="3602631075" remote="318763443983991312" Dst="-1" /><file name="profiler.php" server="christianbrooks.net" local="3602631075" remote="318763443983991312" Dst="-1" /><file name="routes.php" server="christianbrooks.net" local="3602631075" remote="318763443987627372" Dst="-1" /><file name="smileys.php" server="christianbrooks.net" local="3602631076" remote="318763443983991312" Dst="-1" /><file name="user_agents.php" server="christianbrooks.net" local="3602631076" remote="318763443983991312" Dst="-1" /></dwsync>